LICENSE
MANIFEST.in
README.md
requirements-dev.txt
requirements.txt
setup.py
sesemi/__init__.py
sesemi/collation.py
sesemi/datamodules.py
sesemi/datasets.py
sesemi/learners.py
sesemi/losses.py
sesemi/transforms.py
sesemi/utils.py
sesemi.egg-info/PKG-INFO
sesemi.egg-info/SOURCES.txt
sesemi.egg-info/dependency_links.txt
sesemi.egg-info/entry_points.txt
sesemi.egg-info/requires.txt
sesemi.egg-info/top_level.txt
sesemi/config/__init__.py
sesemi/config/resolvers.py
sesemi/config/structs.py
sesemi/models/__init__.py
sesemi/models/utils.py
sesemi/models/backbones/__init__.py
sesemi/models/backbones/base.py
sesemi/models/backbones/resnet.py
sesemi/models/backbones/timm.py
sesemi/models/heads/__init__.py
sesemi/models/heads/base.py
sesemi/models/heads/loss.py
sesemi/ops/__init__.py
sesemi/ops/inference.py
sesemi/ops/pseudo_dataset.py
sesemi/ops/conf/__init__.py
sesemi/ops/conf/imagewang_noisy_student_pseudo_dataset.yaml
sesemi/schedulers/__init__.py
sesemi/schedulers/lr.py
sesemi/schedulers/weight.py
sesemi/trainer/__init__.py
sesemi/trainer/__main__.py
sesemi/trainer/cli.py
sesemi/trainer/conf/__init__.py
sesemi/trainer/conf/cifar10.yaml
sesemi/trainer/conf/cifar100.yaml
sesemi/trainer/conf/imagewang.yaml
sesemi/trainer/conf/imagewang_consistency.yaml
sesemi/trainer/conf/imagewang_entmin.yaml
sesemi/trainer/conf/imagewang_fixmatch.yaml
sesemi/trainer/conf/imagewang_fixmatch_randaugment.yaml
sesemi/trainer/conf/imagewang_jigsaw.yaml
sesemi/trainer/conf/imagewang_jigsaw_entmin.yaml
sesemi/trainer/conf/imagewang_noisy_student_stage_1.yaml
sesemi/trainer/conf/imagewang_noisy_student_stage_n.yaml
sesemi/trainer/conf/imagewang_rotation.yaml
sesemi/trainer/conf/imagewang_rotation_entmin.yaml
sesemi/trainer/conf/imagewoof.yaml
sesemi/trainer/conf/imagewoof_entmin.yaml
sesemi/trainer/conf/imagewoof_rotation.yaml
sesemi/trainer/conf/stl10.yaml
sesemi/trainer/conf/base/config.yaml
sesemi/trainer/conf/base/consistency_minimization/model.yaml
sesemi/trainer/conf/base/entropy_minimization/model.yaml
sesemi/trainer/conf/base/entropy_minimization/data/imagenet.yaml
sesemi/trainer/conf/base/entropy_minimization/data/imagewang.yaml
