Metadata-Version: 2.1
Name: sesemi
Version: 0.3.0
Summary: Image Classification with Self-Supervised Regularization
Home-page: https://github.com/FlyreelAI/sesemi/
Author: Flyreel AI
Author-email: ai@flyreel.co
License: UNKNOWN
Platform: UNKNOWN
Classifier: Programming Language :: Python :: 3
Classifier: Topic :: Scientific/Engineering :: Artificial Intelligence
Classifier: Topic :: Software Development :: Libraries
Classifier: License :: OSI Approved :: Apache Software License
Classifier: Intended Audience :: Science/Research
Classifier: Development Status :: 4 - Beta
License-File: LICENSE
